LICENSE
MANIFEST.in
README.rst
setup.py
btc_template_tables.egg-info/PKG-INFO
btc_template_tables.egg-info/SOURCES.txt
btc_template_tables.egg-info/dependency_links.txt
btc_template_tables.egg-info/requires.txt
btc_template_tables.egg-info/top_level.txt
template_tables/__init__.py
template_tables/apps.py
template_tables/components.py
template_tables/mixins.py
template_tables/views.py
template_tables/static/template_tables/css/default.css
template_tables/static/template_tables/img/sort_icon.svg
template_tables/templates/template_tables/pagination.html
template_tables/templates/template_tables/tables/default.html