Metadata-Version: 1.1
Name: btc-template-tables
Version: 0.4.2
Summary: Some classes for for describing tables with an auto-generated template.
Home-page: https://github.com/MEADez/btc-template-tables
Author: MEADez
Author-email: m3adez@gmail.com
License: BSD License
Platform: UNKNOWN
Classifier: Environment :: Web Environment
Classifier: Framework :: Django
Classifier: Intended Audience :: Developers
Classifier: License :: OSI Approved :: BSD License
Classifier: Operating System :: OS Independent
Classifier: Programming Language :: Python :: 3.7
Classifier: Topic :: Internet :: WWW/HTTP
Classifier: Topic :: Internet :: WWW/HTTP :: Dynamic Content
